pracscode4/installer.py
pracscode4-0.1.dist-info/METADATA
pracscode4-0.1.dist-info/WHEEL
pracscode4-0.1.dist-info/entry_points.txt
pracscode4-0.1.dist-info/top_level.txt
pracscode4-0.1.dist-info/RECORD
